dukpt.py
dukpt-1.0.1.dist-info/LICENSE
dukpt-1.0.1.dist-info/METADATA
dukpt-1.0.1.dist-info/WHEEL
dukpt-1.0.1.dist-info/top_level.txt
dukpt-1.0.1.dist-info/RECORD
