Metadata-Version: 2.1
Name: dukpt
Version: 1.0.1
Requires-Python: >=3.2
License-File: LICENSE
Requires-Dist: bitstring ==3.1.5
Requires-Dist: pycryptodome ==3.14.1
